func ret: 3 

a: 1 

a: 2 

a: 3 

div: 3.0 

Disassembly of func:
  2           0 LOAD_CONST               1 (11) 
              3 STORE_FAST               0 (x) 

  3           6 LOAD_FAST                0 (x) 
              9 LOAD_CONST               2 (5) 
             12 INPLACE_AND          
             13 STORE_FAST               0 (x) 

  4          16 LOAD_FAST                0 (x) 
             19 LOAD_CONST               3 (1) 
             22 INPLACE_XOR          
             23 STORE_FAST               0 (x) 

  5          26 LOAD_FAST                0 (x) 
             29 LOAD_CONST               4 (4) 
             32 INPLACE_OR           
             33 STORE_FAST               0 (x) 

  6          36 LOAD_FAST                0 (x) 
             39 LOAD_CONST               1 (11) 
             42 INPLACE_ADD          
             43 STORE_FAST               0 (x) 

  7          46 LOAD_FAST                0 (x) 
             49 LOAD_CONST               5 (3) 
             52 INPLACE_MULTIPLY     
             53 STORE_FAST               0 (x) 

  8          56 LOAD_FAST                0 (x) 
             59 LOAD_CONST               6 (21) 
             62 INPLACE_SUBTRACT     
             63 STORE_FAST               0 (x) 

  9          66 LOAD_FAST                0 (x) 
             69 LOAD_CONST               7 (7) 
             72 INPLACE_MODULO       
             73 STORE_FAST               0 (x) 

 10          76 LOAD_FAST                0 (x) 
             79 RETURN_VALUE         

